ChangeLog
MANIFEST.in
README.md
README.rst
setup.py
doc/index.html
doc/subprocess.html
doc/subprocess2.BackgroundTask.html
doc/subprocess2.Simple.html
doc/subprocess2.html
doc/subprocess2.simple.html
python_subprocess2.egg-info/PKG-INFO
python_subprocess2.egg-info/SOURCES.txt
python_subprocess2.egg-info/dependency_links.txt
python_subprocess2.egg-info/top_level.txt
subprocess2/BackgroundTask.py
subprocess2/__init__.py
subprocess2/simple.py
tests/runTests.py
tests/subprocess2Tests/__init__.py
tests/subprocess2Tests/sleeper.py
tests/subprocess2Tests/slow_printer.py
tests/subprocess2Tests/test_BackgroundTask.py
tests/subprocess2Tests/test_Inheritance.py
tests/subprocess2Tests/test_Popen.py