Metadata-Version: 1.1
Name: python-subprocess2
Version: 2.0.2
Summary: Extensions to the upstream python subprocess module
Home-page: https://github.com/kata198/python-subprocess2
Author: Tim Savannah
Author-email: kata198@gmail.com
License: LGPLv3
Keywords: python,subprocess,Popen,pipe,wait,timeout,terminate,kill,sigterm,sigkill,process,management,waitUpTo,waitOrTerminate
Platform: UNKNOWN
Classifier: Development Status :: 5 - Production/Stable
Classifier: Programming Language :: Python
Classifier: License :: OSI Approved :: GNU Lesser General Public License v3 (LGPLv3)
Classifier: Programming Language :: Python :: 2
Classifier: Programming Language :: Python :: 2.7
Classifier: Programming Language :: Python :: 3
Classifier: Programming Language :: Python :: 3.4
Classifier: Operating System :: POSIX
Classifier: Operating System :: POSIX :: Linux
Classifier: Operating System :: Unix
Classifier: Operating System :: Microsoft :: Windows
Classifier: Topic :: System
